{"$schema":"https://json-schema.org/draft/2020-12/schema","$id":"phases/development-perm-fin-data.schema.json","title":"Development Phase 6 -- Permanent Financing Conversion Downstream Data","description":"Shape of the dataForDownstream object for the permanent financing conversion phase.","type":"object","required":["permanentLoan","conversionDate"],"properties":{"permanentLoan":{"type":"object","required":["amount","rate","termYears","amortizationYears","dscr","ltv"],"properties":{"amount":{"type":"number","minimum":0},"rate":{"type":"number"},"rateType":{"type":"string","enum":["fixed","floating"]},"termYears":{"type":"integer"},"amortizationYears":{"type":"integer"},"ioYears":{"type":"integer"},"dscr":{"type":"number"},"ltv":{"type":"number"},"debtYield":{"type":"number"},"lenderType":{"type":"string","enum":["agency","cmbs","life-company","bank"]},"lender":{"type":"string"},"annualDebtService":{"type":"number"},"prepayment":{"type":"string"}},"additionalProperties":true},"conversionDate":{"type":"string","format":"date","description":"Date of construction-to-permanent conversion."},"gapEquity":{"type":"number","description":"Additional equity required at conversion (0 if none)."},"constructionLoanPayoff":{"type":"number","description":"Construction loan balance at payoff."},"lenderUnderwrittenNOI":{"type":"number","description":"Stabilized NOI as underwritten by permanent lender."}},"additionalProperties":true}
